odoo9_addon_account_check_printing_report_base-9.0.1.0.0-py2.7-nspkg.pth
odoo_addons/account_check_printing_report_base/__openerp__.py
odoo_addons/account_check_printing_report_base/__init__.py
odoo_addons/account_check_printing_report_base/README.rst
odoo_addons/account_check_printing_report_base/security/ir.model.access.csv
odoo_addons/account_check_printing_report_base/report/check_print.py
odoo_addons/account_check_printing_report_base/report/account_check_writing_report.xml
odoo_addons/account_check_printing_report_base/report/__init__.py
odoo_addons/account_check_printing_report_base/models/__init__.py
odoo_addons/account_check_printing_report_base/models/account_payment.py
odoo_addons/account_check_printing_report_base/models/account_payment_check_report.py
odoo_addons/account_check_printing_report_base/models/res_company.py
odoo_addons/account_check_printing_report_base/views/report_check_base.xml
odoo_addons/account_check_printing_report_base/views/account_payment_check_report_view.xml
odoo_addons/account_check_printing_report_base/views/res_company_view.xml
odoo_addons/account_check_printing_report_base/data/account_payment_check_report_data.xml
odoo_addons/account_check_printing_report_base/data/report_paperformat.xml
odoo_addons/account_check_printing_report_base/tests/test_check_printing_report.py
odoo_addons/account_check_printing_report_base/tests/__init__.py
odoo9_addon_account_check_printing_report_base-9.0.1.0.0.dist-info/top_level.txt
odoo9_addon_account_check_printing_report_base-9.0.1.0.0.dist-info/WHEEL
odoo9_addon_account_check_printing_report_base-9.0.1.0.0.dist-info/RECORD
odoo9_addon_account_check_printing_report_base-9.0.1.0.0.dist-info/metadata.json
odoo9_addon_account_check_printing_report_base-9.0.1.0.0.dist-info/DESCRIPTION.rst
odoo9_addon_account_check_printing_report_base-9.0.1.0.0.dist-info/METADATA
odoo9_addon_account_check_printing_report_base-9.0.1.0.0.dist-info/namespace_packages.txt
